{"v":"4.8.0","meta":{"g":"LottieFiles AE ","a":"","k":"","d":"","tc":""},"fr":60,"ip":0,"op":120,"w":420,"h":360,"nm":"Property 1=sipCancel","ddd":0,"assets":[{"id":"comp_0","layers":[{"ddd":0,"ind":2,"ty":4,"nm":"Vector (Stroke)","sr":1,"ks":{"o":{"a":0,"k":100,"ix":11},"r":{"a":0,"k":0,"ix":10},"p":{"a":0,"k":[268,92,0],"ix":2},"a":{"a":0,"k":[-41,1,0],"ix":1},"s":{"a":0,"k":[100,100,100],"ix":6}},"ao":0,"shapes":[{"ty":"gr","it":[{"ind":0,"ty":"sh","ix":1,"ks":{"a":1,"k":[{"i":{"x":0.833,"y":0.833},"o":{"x":0.167,"y":0.167},"t":22,"s":[{"i":[[0,0],[0.807,0.794],[0.784,-0.818],[0,0],[0,0],[0.807,-0.794],[-0.784,-0.818],[0,0],[-0.551,0],[-0.384,0.401]],"o":[[0.784,-0.818],[-0.807,-0.794],[0,0],[0,0],[-0.784,-0.818],[-0.807,0.794],[0,0],[0.384,0.401],[0.551,0],[0,0]],"v":[[0.508,5.336],[0.465,2.416],[-2.415,2.46],[-3.361,3.471],[-7.501,-0.853],[-10.382,-0.897],[-10.425,2.023],[-4.823,7.873],[-3.361,8.5],[-1.899,7.873]],"c":true}]},{"t":59,"s":[{"i":[[0,0],[0.807,0.794],[0.784,-0.818],[0,0],[0,0],[0.807,-0.794],[-0.784,-0.818],[0,0],[-0.551,0],[-0.384,0.401]],"o":[[0.784,-0.818],[-0.807,-0.794],[0,0],[0,0],[-0.784,-0.818],[-0.807,0.794],[0,0],[0.384,0.401],[0.551,0],[0,0]],"v":[[10.591,-5.164],[10.548,-8.084],[7.668,-8.04],[-3.361,3.471],[-7.501,-0.853],[-10.382,-0.897],[-10.425,2.023],[-4.823,7.873],[-3.361,8.5],[-1.899,7.873]],"c":true}]}],"ix":2},"nm":"Path 1","mn":"ADBE Vector Shape - Group","hd":false},{"ty":"fl","c":{"a":0,"k":[1,1,1,1],"ix":4},"o":{"a":0,"k":100,"ix":5},"r":1,"bm":0,"nm":"Fill 1","mn":"ADBE Vector Graphic - Fill","hd":false},{"ty":"tr","p":{"a":0,"k":[0,0],"ix":2},"a":{"a":0,"k":[0,0],"ix":1},"s":{"a":0,"k":[300,300],"ix":3},"r":{"a":0,"k":0,"ix":6},"o":{"a":1,"k":[{"i":{"x":[0.833],"y":[0.833]},"o":{"x":[0.167],"y":[0.167]},"t":19,"s":[0]},{"t":43,"s":[100]}],"ix":7},"sk":{"a":0,"k":0,"ix":4},"sa":{"a":0,"k":0,"ix":5},"nm":"Transform"}],"nm":"Vector (Stroke)","np":2,"cix":2,"bm":0,"ix":1,"mn":"ADBE Vector Group","hd":false}],"ip":0,"op":300,"st":0,"bm":0},{"ddd":0,"ind":3,"ty":4,"nm":"Vector","sr":1,"ks":{"o":{"a":0,"k":100,"ix":11},"r":{"a":0,"k":0,"ix":10},"p":{"a":0,"k":[303.268,93.104,0],"ix":2},"a":{"a":0,"k":[0,0,0],"ix":1},"s":{"a":0,"k":[100,100,100],"ix":6}},"ao":0,"shapes":[{"ty":"gr","it":[{"ind":0,"ty":"sh","ix":1,"ks":{"a":0,"k":{"i":[[-3.445,2.186],[-4.065,0.384],[0,0],[-3.806,-1.507],[-2.698,-3.072],[-0.996,-3.961],[0.925,-3.978],[2.643,-3.119],[3.779,-1.574],[4.083,0.318],[3.488,2.139],[0,0],[0.236,0.068],[0.163,0.184],[0.038,0.242],[-0.099,0.225],[0,0],[-0.241,4.064],[-2.07,3.51]],"o":[[3.445,-2.186],[0,0],[4.077,-0.39],[3.806,1.507],[2.698,3.072],[0.996,3.961],[-0.925,3.978],[-2.643,3.119],[-3.779,1.574],[-4.083,-0.318],[0,0],[-0.236,0.069],[-0.236,-0.068],[-0.163,-0.184],[-0.038,-0.242],[0,0],[-1.64,-3.729],[0.241,-4.064],[2.07,-3.51]],"v":[[-11.799,-22.007],[-0.372,-25.917],[-0.376,-25.917],[11.618,-24.218],[21.514,-17.252],[27.135,-6.552],[27.243,5.526],[21.814,16.323],[12.043,23.464],[0.081,25.375],[-11.438,21.637],[-26.254,25.982],[-26.977,25.984],[-27.588,25.598],[-27.895,24.946],[-27.802,24.231],[-21.575,10.04],[-23.704,-1.817],[-20.188,-13.34]],"c":true},"ix":2},"nm":"Path 1","mn":"ADBE Vector Shape - Group","hd":false},{"ty":"fl","c":{"a":0,"k":[0.199739575386,0.8125,0.563310742378,1],"ix":4},"o":{"a":0,"k":100,"ix":5},"r":1,"bm":0,"nm":"Fill 1","mn":"ADBE Vector Graphic - Fill","hd":false},{"ty":"tr","p":{"a":0,"k":[0,0],"ix":2},"a":{"a":0,"k":[0,0],"ix":1},"s":{"a":0,"k":[300,300],"ix":3},"r":{"a":0,"k":0,"ix":6},"o":{"a":0,"k":100,"ix":7},"sk":{"a":0,"k":0,"ix":4},"sa":{"a":0,"k":0,"ix":5},"nm":"Transform"}],"nm":"Vector","np":2,"cix":2,"bm":0,"ix":1,"mn":"ADBE Vector Group","hd":false}],"ip":0,"op":300,"st":0,"bm":0}]},{"id":"comp_1","layers":[{"ddd":0,"ind":1,"ty":4,"nm":"Vector","sr":1,"ks":{"o":{"a":0,"k":100,"ix":11},"r":{"a":0,"k":0,"ix":10},"p":{"a":0,"k":[89.281,119.788,0],"ix":2},"a":{"a":0,"k":[0,0,0],"ix":1},"s":{"a":0,"k":[100,100,100],"ix":6}},"ao":0,"shapes":[{"ty":"gr","it":[{"ind":0,"ty":"sh","ix":1,"ks":{"a":0,"k":{"i":[[0,0],[0.115,0.766],[0,0],[-1.443,2.138],[-2.514,0.6],[-2.258,-1.254],[-0.811,-2.447],[0.276,-1.626],[1,-1.313],[0.255,-0.093],[0.264,0.063],[0.185,0.199],[0.044,0.267],[-0.05,0.182],[-0.118,0.148],[-0.187,1.23],[0.419,1.172],[0.925,0.835],[1.211,0.3],[1.209,-0.307],[0.919,-0.841],[0.411,-1.174],[-0.195,-1.229],[-0.364,-0.693]],"o":[[-0.293,-0.717],[0,0],[-0.389,-2.548],[1.443,-2.138],[2.514,-0.6],[2.258,1.254],[0.512,1.568],[-0.276,1.626],[-0.161,0.218],[-0.255,0.093],[-0.264,-0.063],[-0.185,-0.199],[-0.026,-0.187],[0.05,-0.182],[0.748,-0.995],[0.187,-1.23],[-0.419,-1.172],[-0.925,-0.835],[-1.211,-0.3],[-1.209,0.307],[-0.919,0.841],[-0.411,1.174],[0.118,0.774],[0,0]],"v":[[-9.574,5.582],[-10.187,3.349],[-10.186,3.353],[-8.547,-3.934],[-2.393,-8.193],[5.028,-7.177],[9.801,-1.421],[10.16,3.441],[8.219,7.915],[7.58,8.393],[6.784,8.438],[6.095,8.036],[5.745,7.322],[5.781,6.762],[6.036,6.263],[7.46,2.873],[7.107,-0.785],[5.06,-3.842],[1.807,-5.57],[-1.878,-5.558],[-5.121,-3.81],[-7.148,-0.74],[-7.478,2.92],[-6.75,5.135]],"c":true},"ix":2},"nm":"Path 1","mn":"ADBE Vector Shape - Group","hd":false},{"ty":"fl","c":{"a":0,"k":[0.7254901960784313,0.6196078431372549,1,1],"ix":4},"o":{"a":0,"k":100,"ix":5},"r":1,"bm":0,"nm":"Fill 1","mn":"ADBE Vector Graphic - Fill","hd":false},{"ty":"tr","p":{"a":0,"k":[0,0],"ix":2},"a":{"a":0,"k":[0,0],"ix":1},"s":{"a":0,"k":[300,300],"ix":3},"r":{"a":0,"k":0,"ix":6},"o":{"a":0,"k":100,"ix":7},"sk":{"a":0,"k":0,"ix":4},"sa":{"a":0,"k":0,"ix":5},"nm":"Transform"}],"nm":"Vector","np":2,"cix":2,"bm":0,"ix":1,"mn":"ADBE Vector Group","hd":false}],"ip":0,"op":300,"st":0,"bm":0},{"ddd":0,"ind":2,"ty":4,"nm":"Vector","sr":1,"ks":{"o":{"a":0,"k":100,"ix":11},"r":{"a":0,"k":0,"ix":10},"p":{"a":0,"k":[134.077,112.704,0],"ix":2},"a":{"a":0,"k":[0,0,0],"ix":1},"s":{"a":0,"k":[100,100,100],"ix":6}},"ao":0,"shapes":[{"ty":"gr","it":[{"ind":0,"ty":"sh","ix":1,"ks":{"a":0,"k":{"i":[[0,0],[0.115,0.766],[0,0],[-1.443,2.138],[-2.514,0.6],[-2.258,-1.254],[-0.811,-2.447],[0.275,-1.626],[0.999,-1.314],[0.255,-0.093],[0.264,0.063],[0.185,0.199],[0.044,0.267],[-0.05,0.182],[-0.118,0.148],[-0.186,1.229],[0.419,1.171],[0.924,0.834],[1.21,0.299],[1.208,-0.307],[0.919,-0.84],[0.412,-1.173],[-0.193,-1.228],[-0.364,-0.693]],"o":[[-0.293,-0.717],[0,0],[-0.389,-2.548],[1.443,-2.138],[2.514,-0.6],[2.258,1.254],[0.512,1.568],[-0.275,1.626],[-0.161,0.218],[-0.255,0.093],[-0.264,-0.063],[-0.185,-0.199],[-0.026,-0.187],[0.05,-0.182],[0.746,-0.996],[0.186,-1.229],[-0.419,-1.171],[-0.924,-0.834],[-1.21,-0.299],[-1.208,0.307],[-0.919,0.84],[-0.412,1.173],[0.118,0.774],[0,0]],"v":[[-9.576,5.582],[-10.19,3.349],[-10.187,3.353],[-8.548,-3.934],[-2.394,-8.193],[5.027,-7.177],[9.8,-1.421],[10.162,3.44],[8.224,7.915],[7.586,8.393],[6.789,8.438],[6.1,8.036],[5.75,7.322],[5.786,6.762],[6.041,6.263],[7.46,2.874],[7.104,-0.782],[5.057,-3.836],[1.806,-5.562],[-1.878,-5.55],[-5.119,-3.804],[-7.147,-0.738],[-7.48,2.92],[-6.752,5.135]],"c":true},"ix":2},"nm":"Path 1","mn":"ADBE Vector Shape - Group","hd":false},{"ty":"fl","c":{"a":0,"k":[0.7254901960784313,0.6196078431372549,1,1],"ix":4},"o":{"a":0,"k":100,"ix":5},"r":1,"bm":0,"nm":"Fill 1","mn":"ADBE Vector Graphic - Fill","hd":false},{"ty":"tr","p":{"a":0,"k":[0,0],"ix":2},"a":{"a":0,"k":[0,0],"ix":1},"s":{"a":0,"k":[300,300],"ix":3},"r":{"a":0,"k":0,"ix":6},"o":{"a":0,"k":100,"ix":7},"sk":{"a":0,"k":0,"ix":4},"sa":{"a":0,"k":0,"ix":5},"nm":"Transform"}],"nm":"Vector","np":2,"cix":2,"bm":0,"ix":1,"mn":"ADBE Vector Group","hd":false}],"ip":0,"op":300,"st":0,"bm":0},{"ddd":0,"ind":3,"ty":4,"nm":"Vector","sr":1,"ks":{"o":{"a":0,"k":100,"ix":11},"r":{"a":0,"k":0,"ix":10},"p":{"a":0,"k":[178.862,105.62,0],"ix":2},"a":{"a":0,"k":[0,0,0],"ix":1},"s":{"a":0,"k":[100,100,100],"ix":6}},"ao":0,"shapes":[{"ty":"gr","it":[{"ind":0,"ty":"sh","ix":1,"ks":{"a":0,"k":{"i":[[0,0],[0.115,0.766],[0,0],[-1.443,2.138],[-2.514,0.6],[-2.258,-1.254],[-0.811,-2.447],[0.275,-1.626],[0.999,-1.314],[0.255,-0.093],[0.264,0.063],[0.185,0.199],[0.044,0.267],[-0.05,0.182],[-0.118,0.148],[-0.186,1.229],[0.419,1.171],[0.925,0.834],[1.21,0.299],[1.208,-0.307],[0.919,-0.84],[0.412,-1.174],[-0.194,-1.228],[-0.364,-0.693]],"o":[[-0.293,-0.717],[0,0],[-0.389,-2.548],[1.443,-2.138],[2.514,-0.6],[2.258,1.254],[0.512,1.568],[-0.275,1.626],[-0.161,0.218],[-0.255,0.093],[-0.264,-0.063],[-0.185,-0.199],[-0.026,-0.187],[0.05,-0.182],[0.747,-0.996],[0.186,-1.229],[-0.419,-1.171],[-0.925,-0.834],[-1.21,-0.299],[-1.208,0.307],[-0.919,0.84],[-0.412,1.174],[0.118,0.774],[0,0]],"v":[[-9.573,5.582],[-10.187,3.349],[-10.187,3.353],[-8.548,-3.934],[-2.394,-8.193],[5.027,-7.177],[9.8,-1.421],[10.162,3.44],[8.224,7.915],[7.586,8.393],[6.789,8.438],[6.1,8.036],[5.75,7.322],[5.786,6.762],[6.041,6.263],[7.462,2.873],[7.107,-0.783],[5.06,-3.838],[1.808,-5.564],[-1.876,-5.553],[-5.118,-3.806],[-7.145,-0.739],[-7.478,2.92],[-6.75,5.135]],"c":true},"ix":2},"nm":"Path 1","mn":"ADBE Vector Shape - Group","hd":false},{"ty":"fl","c":{"a":0,"k":[0.7254901960784313,0.6196078431372549,1,1],"ix":4},"o":{"a":0,"k":100,"ix":5},"r":1,"bm":0,"nm":"Fill 1","mn":"ADBE Vector Graphic - Fill","hd":false},{"ty":"tr","p":{"a":0,"k":[0,0],"ix":2},"a":{"a":0,"k":[0,0],"ix":1},"s":{"a":0,"k":[300,300],"ix":3},"r":{"a":0,"k":0,"ix":6},"o":{"a":0,"k":100,"ix":7},"sk":{"a":0,"k":0,"ix":4},"sa":{"a":0,"k":0,"ix":5},"nm":"Transform"}],"nm":"Vector","np":2,"cix":2,"bm":0,"ix":1,"mn":"ADBE Vector Group","hd":false}],"ip":0,"op":300,"st":0,"bm":0},{"ddd":0,"ind":4,"ty":4,"nm":"Ellipse 44","sr":1,"ks":{"o":{"a":0,"k":100,"ix":11},"r":{"a":0,"k":0,"ix":10},"p":{"a":0,"k":[200.756,129.513,0],"ix":2},"a":{"a":0,"k":[0,0,0],"ix":1},"s":{"a":0,"k":[100,100,100],"ix":6}},"ao":0,"shapes":[{"ty":"gr","it":[{"d":1,"ty":"el","s":{"a":0,"k":[5.115,5.1],"ix":2},"p":{"a":0,"k":[0,0],"ix":3},"nm":"Ellipse Path 1","mn":"ADBE Vector Shape - Ellipse","hd":false},{"ty":"fl","c":{"a":0,"k":[1,1,1,1],"ix":4},"o":{"a":0,"k":100,"ix":5},"r":1,"bm":0,"nm":"Fill 1","mn":"ADBE Vector Graphic - Fill","hd":false},{"ty":"tr","p":{"a":0,"k":[0,0],"ix":2},"a":{"a":0,"k":[0,0],"ix":1},"s":{"a":0,"k":[300,300],"ix":3},"r":{"a":0,"k":0,"ix":6},"o":{"a":0,"k":100,"ix":7},"sk":{"a":0,"k":0,"ix":4},"sa":{"a":0,"k":0,"ix":5},"nm":"Transform"}],"nm":"Ellipse 44","np":2,"cix":2,"bm":0,"ix":1,"mn":"ADBE Vector Group","hd":false}],"ip":0,"op":300,"st":0,"bm":0},{"ddd":0,"ind":5,"ty":4,"nm":"Ellipse 43","sr":1,"ks":{"o":{"a":0,"k":100,"ix":11},"r":{"a":0,"k":0,"ix":10},"p":{"a":0,"k":[157.786,135.634,0],"ix":2},"a":{"a":0,"k":[0,0,0],"ix":1},"s":{"a":0,"k":[100,100,100],"ix":6}},"ao":0,"shapes":[{"ty":"gr","it":[{"d":1,"ty":"el","s":{"a":0,"k":[5.115,5.1],"ix":2},"p":{"a":0,"k":[0,0],"ix":3},"nm":"Ellipse Path 1","mn":"ADBE Vector Shape - Ellipse","hd":false},{"ty":"fl","c":{"a":0,"k":[1,1,1,1],"ix":4},"o":{"a":0,"k":100,"ix":5},"r":1,"bm":0,"nm":"Fill 1","mn":"ADBE Vector Graphic - Fill","hd":false},{"ty":"tr","p":{"a":0,"k":[0,0],"ix":2},"a":{"a":0,"k":[0,0],"ix":1},"s":{"a":0,"k":[300,300],"ix":3},"r":{"a":0,"k":0,"ix":6},"o":{"a":0,"k":100,"ix":7},"sk":{"a":0,"k":0,"ix":4},"sa":{"a":0,"k":0,"ix":5},"nm":"Transform"}],"nm":"Ellipse 43","np":2,"cix":2,"bm":0,"ix":1,"mn":"ADBE Vector Group","hd":false}],"ip":0,"op":300,"st":0,"bm":0},{"ddd":0,"ind":6,"ty":4,"nm":"Ellipse 42","sr":1,"ks":{"o":{"a":0,"k":100,"ix":11},"r":{"a":0,"k":0,"ix":10},"p":{"a":0,"k":[111.746,141.754,0],"ix":2},"a":{"a":0,"k":[0,0,0],"ix":1},"s":{"a":0,"k":[100,100,100],"ix":6}},"ao":0,"shapes":[{"ty":"gr","it":[{"d":1,"ty":"el","s":{"a":0,"k":[5.115,5.1],"ix":2},"p":{"a":0,"k":[0,0],"ix":3},"nm":"Ellipse Path 1","mn":"ADBE Vector Shape - Ellipse","hd":false},{"ty":"fl","c":{"a":0,"k":[1,1,1,1],"ix":4},"o":{"a":0,"k":100,"ix":5},"r":1,"bm":0,"nm":"Fill 1","mn":"ADBE Vector Graphic - Fill","hd":false},{"ty":"tr","p":{"a":0,"k":[0,0],"ix":2},"a":{"a":0,"k":[0,0],"ix":1},"s":{"a":0,"k":[300,300],"ix":3},"r":{"a":0,"k":0,"ix":6},"o":{"a":0,"k":100,"ix":7},"sk":{"a":0,"k":0,"ix":4},"sa":{"a":0,"k":0,"ix":5},"nm":"Transform"}],"nm":"Ellipse 42","np":2,"cix":2,"bm":0,"ix":1,"mn":"ADBE Vector Group","hd":false}],"ip":0,"op":300,"st":0,"bm":0},{"ddd":0,"ind":7,"ty":0,"nm":"paper","refId":"comp_2","sr":1,"ks":{"o":{"a":0,"k":100,"ix":11},"r":{"a":0,"k":0,"ix":10},"p":{"a":0,"k":[210,180,0],"ix":2},"a":{"a":0,"k":[210,180,0],"ix":1},"s":{"a":0,"k":[100,100,100],"ix":6}},"ao":0,"w":420,"h":360,"ip":0,"op":300,"st":0,"bm":0},{"ddd":0,"ind":8,"ty":4,"nm":"Vector","sr":1,"ks":{"o":{"a":0,"k":100,"ix":11},"r":{"a":0,"k":0,"ix":10},"p":{"a":0,"k":[153.738,143.068,0],"ix":2},"a":{"a":0,"k":[0,0,0],"ix":1},"s":{"a":0,"k":[100,100,100],"ix":6}},"ao":0,"shapes":[{"ty":"gr","it":[{"ind":0,"ty":"sh","ix":1,"ks":{"a":0,"k":{"i":[[0,0],[0,0],[0,0],[0.094,0.153],[0.146,0.106],[0.176,0.042],[0.178,-0.028],[0,0],[0.154,-0.094],[0.106,-0.146],[0.042,-0.175],[-0.028,-0.178]],"o":[[0,0],[0,0],[-0.028,-0.178],[-0.094,-0.153],[-0.146,-0.106],[-0.176,-0.042],[0,0],[-0.178,0.028],[-0.154,0.094],[-0.106,0.146],[-0.042,0.175],[0,0]],"v":[[-23.449,10.569],[25.414,2.841],[23.465,-9.413],[23.279,-9.915],[22.915,-10.307],[22.428,-10.531],[21.892,-10.552],[-24.255,-3.252],[-24.758,-3.068],[-25.152,-2.705],[-25.376,-2.22],[-25.397,-1.686]],"c":true},"ix":2},"nm":"Path 1","mn":"ADBE Vector Shape - Group","hd":false},{"ty":"fl","c":{"a":0,"k":[0.4196078431372549,0.25098039215686274,0.8666666666666667,1],"ix":4},"o":{"a":0,"k":100,"ix":5},"r":1,"bm":0,"nm":"Fill 1","mn":"ADBE Vector Graphic - Fill","hd":false},{"ty":"tr","p":{"a":0,"k":[0,0],"ix":2},"a":{"a":0,"k":[0,0],"ix":1},"s":{"a":0,"k":[300,300],"ix":3},"r":{"a":0,"k":0,"ix":6},"o":{"a":0,"k":100,"ix":7},"sk":{"a":0,"k":0,"ix":4},"sa":{"a":0,"k":0,"ix":5},"nm":"Transform"}],"nm":"Vector","np":2,"cix":2,"bm":0,"ix":1,"mn":"ADBE Vector Group","hd":false}],"ip":0,"op":300,"st":0,"bm":0},{"ddd":0,"ind":9,"ty":4,"nm":"Vector","sr":1,"ks":{"o":{"a":0,"k":100,"ix":11},"r":{"a":0,"k":0,"ix":10},"p":{"a":0,"k":[162.076,197.464,0],"ix":2},"a":{"a":0,"k":[0,0,0],"ix":1},"s":{"a":0,"k":[100,100,100],"ix":6}},"ao":0,"shapes":[{"ty":"gr","it":[{"ind":0,"ty":"sh","ix":1,"ks":{"a":0,"k":{"i":[[0,0],[0,0],[0,0],[0,0]],"o":[[0,0],[0,0],[0,0],[0,0]],"v":[[24.735,-24.289],[-24.735,-24.289],[-24.735,24.289],[24.735,24.289]],"c":true},"ix":2},"nm":"Path 1","mn":"ADBE Vector Shape - Group","hd":false},{"ty":"fl","c":{"a":0,"k":[0.8313725490196079,0.7647058823529411,1,1],"ix":4},"o":{"a":0,"k":100,"ix":5},"r":1,"bm":0,"nm":"Fill 1","mn":"ADBE Vector Graphic - Fill","hd":false},{"ty":"tr","p":{"a":0,"k":[0,0],"ix":2},"a":{"a":0,"k":[0,0],"ix":1},"s":{"a":0,"k":[300,300],"ix":3},"r":{"a":0,"k":-9.039,"ix":6},"o":{"a":0,"k":100,"ix":7},"sk":{"a":0,"k":0,"ix":4},"sa":{"a":0,"k":0,"ix":5},"nm":"Transform"}],"nm":"Vector","np":2,"cix":2,"bm":0,"ix":1,"mn":"ADBE Vector Group","hd":false}],"ip":0,"op":300,"st":0,"bm":0},{"ddd":0,"ind":10,"ty":4,"nm":"Vector","sr":1,"ks":{"o":{"a":0,"k":100,"ix":11},"r":{"a":0,"k":0,"ix":10},"p":{"a":0,"k":[132.506,200.536,0],"ix":2},"a":{"a":0,"k":[0,0,0],"ix":1},"s":{"a":0,"k":[100,100,100],"ix":6}},"ao":0,"shapes":[{"ty":"gr","it":[{"ind":0,"ty":"sh","ix":1,"ks":{"a":0,"k":{"i":[[0,0],[0,0],[0,0],[0,0]],"o":[[0,0],[0,0],[0,0],[0,0]],"v":[[24.735,-24.817],[-24.735,-24.817],[-24.735,24.817],[24.735,24.817]],"c":true},"ix":2},"nm":"Path 1","mn":"ADBE Vector Shape - Group","hd":false},{"ty":"rd","nm":"Round Corners 1","r":{"a":0,"k":2,"ix":1},"ix":2,"mn":"ADBE Vector Filter - RC","hd":false},{"ty":"fl","c":{"a":0,"k":[0.7254901960784313,0.6196078431372549,1,1],"ix":4},"o":{"a":0,"k":100,"ix":5},"r":1,"bm":0,"nm":"Fill 1","mn":"ADBE Vector Graphic - Fill","hd":false},{"ty":"tr","p":{"a":0,"k":[0,0],"ix":2},"a":{"a":0,"k":[0,0],"ix":1},"s":{"a":0,"k":[300,300],"ix":3},"r":{"a":0,"k":-9.039,"ix":6},"o":{"a":0,"k":100,"ix":7},"sk":{"a":0,"k":0,"ix":4},"sa":{"a":0,"k":0,"ix":5},"nm":"Transform"}],"nm":"Vector","np":3,"cix":2,"bm":0,"ix":1,"mn":"ADBE Vector Group","hd":false}],"ip":0,"op":300,"st":0,"bm":0},{"ddd":0,"ind":11,"ty":4,"nm":"Vector","sr":1,"ks":{"o":{"a":0,"k":100,"ix":11},"r":{"a":0,"k":0,"ix":10},"p":{"a":0,"k":[132.506,200.536,0],"ix":2},"a":{"a":0,"k":[0,0,0],"ix":1},"s":{"a":0,"k":[100,100,100],"ix":6}},"ao":0,"shapes":[{"ty":"gr","it":[{"ind":0,"ty":"sh","ix":1,"ks":{"a":0,"k":{"i":[[0,0],[0,0],[0,0],[0,0]],"o":[[0,0],[0,0],[0,0],[0,0]],"v":[[24.735,-24.817],[-24.735,-24.817],[-24.735,24.817],[24.735,24.817]],"c":true},"ix":2},"nm":"Path 1","mn":"ADBE Vector Shape - Group","hd":false},{"ty":"tr","p":{"a":0,"k":[0,0],"ix":2},"a":{"a":0,"k":[0,0],"ix":1},"s":{"a":0,"k":[300,300],"ix":3},"r":{"a":0,"k":-9.039,"ix":6},"o":{"a":0,"k":100,"ix":7},"sk":{"a":0,"k":0,"ix":4},"sa":{"a":0,"k":0,"ix":5},"nm":"Transform"}],"nm":"Vector","np":1,"cix":2,"bm":0,"ix":1,"mn":"ADBE Vector Group","hd":false}],"ip":0,"op":300,"st":0,"bm":0}]},{"id":"comp_2","layers":[{"ddd":0,"ind":1,"ty":4,"nm":"Vector","sr":1,"ks":{"o":{"a":0,"k":100,"ix":11},"r":{"a":0,"k":0,"ix":10},"p":{"a":0,"k":[177.736,215.2,0],"ix":2},"a":{"a":0,"k":[0,0,0],"ix":1},"s":{"a":0,"k":[100,100,100],"ix":6}},"ao":0,"shapes":[{"ty":"gr","it":[{"ind":0,"ty":"sh","ix":1,"ks":{"a":0,"k":{"i":[[0,0],[0,0]],"o":[[0,0],[0,0]],"v":[[22.508,-4.59],[-22.508,4.59]],"c":false},"ix":2},"nm":"Path 1","mn":"ADBE Vector Shape - Group","hd":false},{"ty":"st","c":{"a":0,"k":[0.24313725490196078,0.10196078431372549,0.615686274509804,1],"ix":3},"o":{"a":0,"k":100,"ix":4},"w":{"a":0,"k":1,"ix":5},"lc":2,"lj":2,"bm":0,"nm":"Stroke 1","mn":"ADBE Vector Graphic - Stroke","hd":false},{"ty":"tr","p":{"a":0,"k":[0,0],"ix":2},"a":{"a":0,"k":[0,0],"ix":1},"s":{"a":0,"k":[300,300],"ix":3},"r":{"a":0,"k":0,"ix":6},"o":{"a":0,"k":100,"ix":7},"sk":{"a":0,"k":0,"ix":4},"sa":{"a":0,"k":0,"ix":5},"nm":"Transform"}],"nm":"Vector","np":2,"cix":2,"bm":0,"ix":1,"mn":"ADBE Vector Group","hd":false}],"ip":0,"op":300,"st":0,"bm":0},{"ddd":0,"ind":2,"ty":4,"nm":"Vector","sr":1,"ks":{"o":{"a":0,"k":100,"ix":11},"r":{"a":0,"k":0,"ix":10},"p":{"a":0,"k":[160.855,190.718,0],"ix":2},"a":{"a":0,"k":[0,0,0],"ix":1},"s":{"a":0,"k":[100,100,100],"ix":6}},"ao":0,"shapes":[{"ty":"gr","it":[{"ind":0,"ty":"sh","ix":1,"ks":{"a":0,"k":{"i":[[0,0],[0,0]],"o":[[0,0],[0,0]],"v":[[23.02,-4.59],[-23.02,4.59]],"c":false},"ix":2},"nm":"Path 1","mn":"ADBE Vector Shape - Group","hd":false},{"ty":"st","c":{"a":0,"k":[0.24313725490196078,0.10196078431372549,0.615686274509804,1],"ix":3},"o":{"a":0,"k":100,"ix":4},"w":{"a":0,"k":1,"ix":5},"lc":2,"lj":2,"bm":0,"nm":"Stroke 1","mn":"ADBE Vector Graphic - Stroke","hd":false},{"ty":"tr","p":{"a":0,"k":[0,0],"ix":2},"a":{"a":0,"k":[0,0],"ix":1},"s":{"a":0,"k":[300,300],"ix":3},"r":{"a":0,"k":0,"ix":6},"o":{"a":0,"k":100,"ix":7},"sk":{"a":0,"k":0,"ix":4},"sa":{"a":0,"k":0,"ix":5},"nm":"Transform"}],"nm":"Vector","np":2,"cix":2,"bm":0,"ix":1,"mn":"ADBE Vector Group","hd":false}],"ip":0,"op":300,"st":0,"bm":0},{"ddd":0,"ind":3,"ty":4,"nm":"Vector","sr":1,"ks":{"o":{"a":0,"k":100,"ix":11},"r":{"a":0,"k":0,"ix":10},"p":{"a":0,"k":[229.914,189.339,0],"ix":2},"a":{"a":0,"k":[0,0,0],"ix":1},"s":{"a":0,"k":[100,100,100],"ix":6}},"ao":0,"shapes":[{"ty":"gr","it":[{"ind":0,"ty":"sh","ix":1,"ks":{"a":0,"k":{"i":[[0,0],[1.704,10.55],[0,0]],"o":[[-10.38,1.079],[0,0],[0,0]],"v":[[11.254,11.171],[-10.41,-6.039],[-11.254,-11.271]],"c":false},"ix":2},"nm":"Path 1","mn":"ADBE Vector Shape - Group","hd":false},{"ty":"st","c":{"a":0,"k":[0.24313725490196078,0.10196078431372549,0.615686274509804,1],"ix":3},"o":{"a":0,"k":100,"ix":4},"w":{"a":0,"k":1,"ix":5},"lc":2,"lj":2,"bm":0,"nm":"Stroke 1","mn":"ADBE Vector Graphic - Stroke","hd":false},{"ty":"tr","p":{"a":0,"k":[0,0],"ix":2},"a":{"a":0,"k":[0,0],"ix":1},"s":{"a":0,"k":[300,300],"ix":3},"r":{"a":0,"k":0,"ix":6},"o":{"a":0,"k":100,"ix":7},"sk":{"a":0,"k":0,"ix":4},"sa":{"a":0,"k":0,"ix":5},"nm":"Transform"}],"nm":"Vector","np":2,"cix":2,"bm":0,"ix":1,"mn":"ADBE Vector Group","hd":false}],"ip":0,"op":300,"st":0,"bm":0},{"ddd":0,"ind":4,"ty":4,"nm":"Vector","sr":1,"ks":{"o":{"a":0,"k":100,"ix":11},"r":{"a":0,"k":0,"ix":10},"p":{"a":0,"k":[196.152,195.58,0],"ix":2},"a":{"a":0,"k":[0,0,0],"ix":1},"s":{"a":0,"k":[100,100,100],"ix":6}},"ao":0,"shapes":[{"ty":"gr","it":[{"ind":0,"ty":"sh","ix":1,"ks":{"a":0,"k":{"i":[[0,0],[4.052,3.117],[0.784,5.177],[0,0]],"o":[[-4.991,0.734],[-4.052,-3.117],[0,0],[0,0]],"v":[[11.254,11.13],[-2.857,7.214],[-10.403,-5.73],[-11.254,-11.312]],"c":false},"ix":2},"nm":"Path 1","mn":"ADBE Vector Shape - Group","hd":false},{"ty":"st","c":{"a":0,"k":[0.24313725490196078,0.10196078431372549,0.615686274509804,1],"ix":3},"o":{"a":0,"k":100,"ix":4},"w":{"a":0,"k":1,"ix":5},"lc":2,"lj":2,"bm":0,"nm":"Stroke 1","mn":"ADBE Vector Graphic - Stroke","hd":false},{"ty":"tr","p":{"a":0,"k":[0,0],"ix":2},"a":{"a":0,"k":[0,0],"ix":1},"s":{"a":0,"k":[300,300],"ix":3},"r":{"a":0,"k":0,"ix":6},"o":{"a":0,"k":100,"ix":7},"sk":{"a":0,"k":0,"ix":4},"sa":{"a":0,"k":0,"ix":5},"nm":"Transform"}],"nm":"Vector","np":2,"cix":2,"bm":0,"ix":1,"mn":"ADBE Vector Group","hd":false}],"ip":0,"op":300,"st":0,"bm":0},{"ddd":0,"ind":5,"ty":4,"nm":"Vector","sr":1,"ks":{"o":{"a":0,"k":100,"ix":11},"r":{"a":0,"k":0,"ix":10},"p":{"a":0,"k":[157.786,201.717,0],"ix":2},"a":{"a":0,"k":[0,0,0],"ix":1},"s":{"a":0,"k":[100,100,100],"ix":6}},"ao":0,"shapes":[{"ty":"gr","it":[{"ind":0,"ty":"sh","ix":1,"ks":{"a":0,"k":{"i":[[0,0],[3.864,3.07],[0.735,5.112],[0,0]],"o":[[-4.749,0.755],[-3.864,-3.07],[0,0],[0,0]],"v":[[10.743,11.125],[-2.704,7.301],[-9.883,-5.474],[-10.743,-11.317]],"c":false},"ix":2},"nm":"Path 1","mn":"ADBE Vector Shape - Group","hd":false},{"ty":"st","c":{"a":0,"k":[0.24313725490196078,0.10196078431372549,0.615686274509804,1],"ix":3},"o":{"a":0,"k":100,"ix":4},"w":{"a":0,"k":1,"ix":5},"lc":2,"lj":2,"bm":0,"nm":"Stroke 1","mn":"ADBE Vector Graphic - Stroke","hd":false},{"ty":"tr","p":{"a":0,"k":[0,0],"ix":2},"a":{"a":0,"k":[0,0],"ix":1},"s":{"a":0,"k":[300,300],"ix":3},"r":{"a":0,"k":0,"ix":6},"o":{"a":0,"k":100,"ix":7},"sk":{"a":0,"k":0,"ix":4},"sa":{"a":0,"k":0,"ix":5},"nm":"Transform"}],"nm":"Vector","np":2,"cix":2,"bm":0,"ix":1,"mn":"ADBE Vector Group","hd":false}],"ip":0,"op":300,"st":0,"bm":0},{"ddd":0,"ind":6,"ty":4,"nm":"Vector","sr":1,"ks":{"o":{"a":0,"k":100,"ix":11},"r":{"a":0,"k":0,"ix":10},"p":{"a":0,"k":[156.251,163.176,0],"ix":2},"a":{"a":0,"k":[0,0,0],"ix":1},"s":{"a":0,"k":[100,100,100],"ix":6}},"ao":0,"shapes":[{"ty":"gr","it":[{"ind":0,"ty":"sh","ix":1,"ks":{"a":0,"k":{"i":[[0,0],[0,0]],"o":[[0,0],[0,0]],"v":[[23.531,-3.57],[-23.531,3.57]],"c":false},"ix":2},"nm":"Path 1","mn":"ADBE Vector Shape - Group","hd":false},{"ty":"st","c":{"a":0,"k":[0.24313725490196078,0.10196078431372549,0.615686274509804,1],"ix":3},"o":{"a":0,"k":100,"ix":4},"w":{"a":0,"k":1,"ix":5},"lc":2,"lj":2,"bm":0,"nm":"Stroke 1","mn":"ADBE Vector Graphic - Stroke","hd":false},{"ty":"tr","p":{"a":0,"k":[0,0],"ix":2},"a":{"a":0,"k":[0,0],"ix":1},"s":{"a":0,"k":[300,300],"ix":3},"r":{"a":0,"k":0,"ix":6},"o":{"a":0,"k":100,"ix":7},"sk":{"a":0,"k":0,"ix":4},"sa":{"a":0,"k":0,"ix":5},"nm":"Transform"}],"nm":"Vector","np":2,"cix":2,"bm":0,"ix":1,"mn":"ADBE Vector Group","hd":false}],"ip":0,"op":300,"st":0,"bm":0},{"ddd":0,"ind":7,"ty":4,"nm":"Vector","sr":1,"ks":{"o":{"a":0,"k":100,"ix":11},"r":{"a":0,"k":0,"ix":10},"p":{"a":0,"k":[189.79,112.01,0],"ix":2},"a":{"a":0,"k":[0.609,-65.287,0],"ix":1},"s":{"a":0,"k":[100,100,100],"ix":6}},"ao":0,"shapes":[{"ty":"gr","it":[{"ind":0,"ty":"sh","ix":1,"ks":{"a":0,"k":{"i":[[4.247,3.075],[0.822,5.168],[0,0],[0.094,0.153],[0.146,0.106],[0.176,0.042],[0.178,-0.028],[0,0],[0.154,-0.094],[0.106,-0.146],[0.042,-0.175],[-0.028,-0.178],[0,0],[-1.358,-2.21],[-2.103,-1.523],[-2.527,-0.605],[-2.567,0.406],[0,0]],"o":[[-4.247,-3.075],[0,0],[-0.028,-0.178],[-0.094,-0.153],[-0.146,-0.106],[-0.176,-0.042],[0,0],[-0.178,0.028],[-0.154,0.094],[-0.106,0.146],[-0.042,0.175],[0,0],[0.406,2.56],[1.358,2.21],[2.103,1.523],[2.527,0.605],[0,0],[-5.184,0.82]],"v":[[22.5,10.485],[14.583,-2.389],[11.65,-20.823],[11.465,-21.325],[11.101,-21.717],[10.613,-21.941],[10.078,-21.962],[-36.07,-14.662],[-36.573,-14.477],[-36.966,-14.115],[-37.191,-13.629],[-37.212,-13.095],[-34.28,5.332],[-31.607,12.556],[-26.365,18.211],[-19.351,21.434],[-11.635,21.735],[37.229,14.007]],"c":true},"ix":2},"nm":"Path 1","mn":"ADBE Vector Shape - Group","hd":false},{"ty":"fl","c":{"a":0,"k":[0.4196078431372549,0.25098039215686274,0.8666666666666667,1],"ix":4},"o":{"a":0,"k":100,"ix":5},"r":1,"bm":0,"nm":"Fill 1","mn":"ADBE Vector Graphic - Fill","hd":false},{"ty":"tr","p":{"a":0,"k":[0.609,0.648],"ix":2},"a":{"a":0,"k":[0,0],"ix":1},"s":{"a":0,"k":[300,300],"ix":3},"r":{"a":0,"k":0,"ix":6},"o":{"a":0,"k":100,"ix":7},"sk":{"a":0,"k":0,"ix":4},"sa":{"a":0,"k":0,"ix":5},"nm":"Transform"}],"nm":"Vector","np":2,"cix":2,"bm":0,"ix":1,"mn":"ADBE Vector Group","hd":false}],"ip":0,"op":300,"st":0,"bm":0},{"ddd":0,"ind":8,"ty":4,"nm":"Vector 2","sr":1,"ks":{"o":{"a":0,"k":100,"ix":11},"r":{"a":0,"k":0,"ix":10},"p":{"a":0,"k":[189.181,177.297,0],"ix":2},"a":{"a":0,"k":[0,0,0],"ix":1},"s":{"a":0,"k":[100,100,100],"ix":6}},"ao":0,"shapes":[{"ty":"gr","it":[{"ind":0,"ty":"sh","ix":1,"ks":{"a":0,"k":{"i":[[4.247,3.075],[0.822,5.168],[0,0],[0.094,0.153],[0.146,0.106],[0.176,0.042],[0.178,-0.028],[0,0],[0.154,-0.094],[0.106,-0.146],[0.042,-0.175],[-0.028,-0.178],[0,0],[-1.358,-2.21],[-2.103,-1.523],[-2.527,-0.605],[-2.567,0.406],[0,0]],"o":[[-4.247,-3.075],[0,0],[-0.028,-0.178],[-0.094,-0.153],[-0.146,-0.106],[-0.176,-0.042],[0,0],[-0.178,0.028],[-0.154,0.094],[-0.106,0.146],[-0.042,0.175],[0,0],[0.406,2.56],[1.358,2.21],[2.103,1.523],[2.527,0.605],[0,0],[-5.184,0.82]],"v":[[22.5,10.485],[14.583,-2.389],[11.65,-20.823],[11.465,-21.325],[11.101,-21.717],[10.613,-21.941],[10.078,-21.962],[-36.07,-14.662],[-36.573,-14.477],[-36.966,-14.115],[-37.191,-13.629],[-37.212,-13.095],[-34.28,5.332],[-31.607,12.556],[-26.365,18.211],[-19.351,21.434],[-11.635,21.735],[37.229,14.007]],"c":true},"ix":2},"nm":"Path 1","mn":"ADBE Vector Shape - Group","hd":false},{"ty":"fl","c":{"a":0,"k":[0.972549021244,0.972549021244,0.980392158031,1],"ix":4},"o":{"a":0,"k":100,"ix":5},"r":1,"bm":0,"nm":"Fill 1","mn":"ADBE Vector Graphic - Fill","hd":false},{"ty":"tr","p":{"a":0,"k":[0,0],"ix":2},"a":{"a":0,"k":[0,0],"ix":1},"s":{"a":0,"k":[300,300],"ix":3},"r":{"a":0,"k":0,"ix":6},"o":{"a":0,"k":100,"ix":7},"sk":{"a":0,"k":0,"ix":4},"sa":{"a":0,"k":0,"ix":5},"nm":"Transform"}],"nm":"Vector","np":2,"cix":2,"bm":0,"ix":1,"mn":"ADBE Vector Group","hd":false}],"ip":0,"op":300,"st":0,"bm":0}]}],"layers":[{"ddd":0,"ind":2,"ty":0,"nm":"complete","refId":"comp_0","sr":1,"ks":{"o":{"a":1,"k":[{"i":{"x":[0.667],"y":[1]},"o":{"x":[0.333],"y":[0]},"t":22,"s":[0]},{"t":38,"s":[100]}],"ix":11},"r":{"a":0,"k":0,"ix":10},"p":{"a":0,"k":[216.452,178.089,0],"ix":2},"a":{"a":0,"k":[210,180,0],"ix":1},"s":{"a":1,"k":[{"i":{"x":[0.667,0.667,0.667],"y":[0.816,0.818,1]},"o":{"x":[0.333,0.333,0.333],"y":[0,0,0]},"t":11,"s":[0,0,100]},{"i":{"x":[0.667,0.667,0.667],"y":[0.558,-2.018,1]},"o":{"x":[0.333,0.333,0.333],"y":[0.857,5.846,0]},"t":35,"s":[105.039,106.039,100]},{"i":{"x":[0.667,0.667,0.667],"y":[1,1,1]},"o":{"x":[0.333,0.333,0.333],"y":[-0.256,-0.37,0]},"t":40,"s":[109.726,106.726,100]},{"t":46,"s":[100,100,100]}],"ix":6}},"ao":0,"w":420,"h":360,"ip":0,"op":300,"st":0,"bm":0},{"ddd":0,"ind":5,"ty":4,"nm":"Vector 2","sr":1,"ks":{"o":{"a":1,"k":[{"i":{"x":[0.833],"y":[0.833]},"o":{"x":[0.167],"y":[0.167]},"t":0,"s":[15]},{"i":{"x":[0.833],"y":[0.833]},"o":{"x":[0.167],"y":[0.167]},"t":58,"s":[7]},{"t":119,"s":[15]}],"ix":11},"r":{"a":0,"k":0,"ix":10},"p":{"a":0,"k":[166.546,302.723,0],"ix":2},"a":{"a":0,"k":[0,0,0],"ix":1},"s":{"a":1,"k":[{"i":{"x":[0.833,0.833,0.833],"y":[0.833,0.833,0.833]},"o":{"x":[0.167,0.167,0.167],"y":[0.167,0.167,0.167]},"t":0,"s":[100,100,100]},{"i":{"x":[0.833,0.833,0.833],"y":[0.833,0.833,0.833]},"o":{"x":[0.167,0.167,0.167],"y":[0.167,0.167,0.167]},"t":58,"s":[80,80,100]},{"t":119,"s":[100,100,100]}],"ix":6}},"ao":0,"shapes":[{"ty":"gr","it":[{"ind":0,"ty":"sh","ix":1,"ks":{"a":0,"k":{"i":[[1.098,0.26],[0,0.281],[0,0],[-1.098,0.26],[-2.029,0.199],[-2.651,0.108],[-2.869,0],[-2.651,-0.108],[-2.029,-0.199],[-1.098,-0.26],[0,-0.281],[1.098,-0.26],[2.029,-0.199],[2.651,-0.108],[2.869,0],[2.651,0.108],[2.029,0.199]],"o":[[-1.098,-0.26],[0,0],[0,-0.281],[1.098,-0.26],[2.029,-0.199],[2.651,-0.108],[2.869,0],[2.651,0.108],[2.029,0.199],[1.098,0.26],[0,0.281],[-1.098,0.26],[-2.029,0.199],[-2.651,0.108],[-2.869,0],[-2.651,-0.108],[-2.029,-0.199]],"v":[[-20.184,0.82],[-21.847,0],[-21.847,0],[-20.184,-0.82],[-15.448,-1.515],[-8.361,-1.979],[0,-2.142],[8.361,-1.979],[15.448,-1.515],[20.184,-0.82],[21.847,0],[20.184,0.82],[15.448,1.515],[8.361,1.979],[0,2.142],[-8.361,1.979],[-15.448,1.515]],"c":true},"ix":2},"nm":"Path 1","mn":"ADBE Vector Shape - Group","hd":false},{"ty":"fl","c":{"a":0,"k":[0.533333361149,0.560784339905,0.686274528503,1],"ix":4},"o":{"a":0,"k":100,"ix":5},"r":1,"bm":0,"nm":"Fill 1","mn":"ADBE Vector Graphic - Fill","hd":false},{"ty":"tr","p":{"a":0,"k":[0,0],"ix":2},"a":{"a":0,"k":[0,0],"ix":1},"s":{"a":0,"k":[300,300],"ix":3},"r":{"a":0,"k":0,"ix":6},"o":{"a":0,"k":100,"ix":7},"sk":{"a":0,"k":0,"ix":4},"sa":{"a":0,"k":0,"ix":5},"nm":"Transform"}],"nm":"Vector","np":2,"cix":2,"bm":0,"ix":1,"mn":"ADBE Vector Group","hd":false}],"ip":0,"op":122,"st":0,"bm":0},{"ddd":0,"ind":6,"ty":0,"nm":"calender","refId":"comp_1","sr":1,"ks":{"o":{"a":0,"k":100,"ix":11},"r":{"a":0,"k":0,"ix":10},"p":{"a":1,"k":[{"i":{"x":0.667,"y":1},"o":{"x":0.333,"y":0},"t":0,"s":[210,180,0],"to":[0,0,0],"ti":[0,0,0]},{"i":{"x":0.667,"y":1},"o":{"x":0.333,"y":0},"t":56,"s":[210,161.729,0],"to":[0,0,0],"ti":[0,0,0]},{"t":120,"s":[210,180,0]}],"ix":2},"a":{"a":0,"k":[210,180,0],"ix":1},"s":{"a":0,"k":[100,100,100],"ix":6}},"ao":0,"w":420,"h":360,"ip":0,"op":300,"st":0,"bm":0},{"ddd":0,"ind":7,"ty":4,"nm":"Vector","sr":1,"ks":{"o":{"a":0,"k":100,"ix":11},"r":{"a":0,"k":0,"ix":10},"p":{"a":0,"k":[183.326,198.109,0],"ix":2},"a":{"a":0,"k":[0,0,0],"ix":1},"s":{"a":0,"k":[100,100,100],"ix":6}},"ao":0,"shapes":[{"ty":"gr","it":[{"ind":0,"ty":"sh","ix":1,"ks":{"a":0,"k":{"i":[[9.21,9.182],[0,12.986],[0,0],[-9.21,9.182],[-13.024,0],[-9.21,-9.182],[0,-12.986],[9.21,-9.182],[13.024,0]],"o":[[-9.21,-9.182],[0,0],[0,-12.986],[9.21,-9.182],[13.024,0],[9.21,9.182],[0,12.986],[-9.21,9.182],[-13.024,0]],"v":[[-34.725,34.623],[-49.109,0],[-49.109,0],[-34.725,-34.623],[0,-48.964],[34.725,-34.623],[49.109,0],[34.725,34.623],[0,48.964]],"c":true},"ix":2},"nm":"Path 1","mn":"ADBE Vector Shape - Group","hd":false},{"ty":"fl","c":{"a":0,"k":[0.9568627450980393,0.9411764705882353,1,1],"ix":4},"o":{"a":0,"k":100,"ix":5},"r":1,"bm":0,"nm":"Fill 1","mn":"ADBE Vector Graphic - Fill","hd":false},{"ty":"tr","p":{"a":0,"k":[0,0],"ix":2},"a":{"a":0,"k":[0,0],"ix":1},"s":{"a":0,"k":[300,300],"ix":3},"r":{"a":0,"k":0,"ix":6},"o":{"a":0,"k":100,"ix":7},"sk":{"a":0,"k":0,"ix":4},"sa":{"a":0,"k":0,"ix":5},"nm":"Transform"}],"nm":"Vector","np":2,"cix":2,"bm":0,"ix":1,"mn":"ADBE Vector Group","hd":false}],"ip":0,"op":131,"st":0,"bm":0},{"ddd":0,"ind":8,"ty":4,"nm":"base","sr":1,"ks":{"o":{"a":0,"k":100,"ix":11},"r":{"a":0,"k":0,"ix":10},"p":{"a":0,"k":[210,180,0],"ix":2},"a":{"a":0,"k":[0,0,0],"ix":1},"s":{"a":0,"k":[100,100,100],"ix":6}},"ao":0,"shapes":[{"ty":"gr","it":[{"ty":"rc","d":1,"s":{"a":0,"k":[130,110],"ix":2},"p":{"a":0,"k":[0,0],"ix":3},"r":{"a":0,"k":0,"ix":4},"nm":"Rectangle Path 1","mn":"ADBE Vector Shape - Rect","hd":false},{"ty":"tr","p":{"a":0,"k":[0,0],"ix":2},"a":{"a":0,"k":[0,0],"ix":1},"s":{"a":0,"k":[300,300],"ix":3},"r":{"a":0,"k":0,"ix":6},"o":{"a":0,"k":100,"ix":7},"sk":{"a":0,"k":0,"ix":4},"sa":{"a":0,"k":0,"ix":5},"nm":"Transform"}],"nm":"base","np":1,"cix":2,"bm":0,"ix":1,"mn":"ADBE Vector Group","hd":false}],"ip":0,"op":148,"st":0,"bm":0},{"ddd":0,"ind":9,"ty":4,"nm":"Property 1=sipCancel","sr":1,"ks":{"o":{"a":0,"k":100,"ix":11},"r":{"a":0,"k":0,"ix":10},"p":{"a":0,"k":[210,180,0],"ix":2},"a":{"a":0,"k":[0,0,0],"ix":1},"s":{"a":0,"k":[100,100,100],"ix":6}},"ao":0,"shapes":[{"ty":"gr","it":[{"ty":"rc","d":1,"s":{"a":0,"k":[140,120],"ix":2},"p":{"a":0,"k":[0,0],"ix":3},"r":{"a":0,"k":0,"ix":4},"nm":"Rectangle Path 1","mn":"ADBE Vector Shape - Rect","hd":false},{"ty":"tr","p":{"a":0,"k":[0,0],"ix":2},"a":{"a":0,"k":[0,0],"ix":1},"s":{"a":0,"k":[300,300],"ix":3},"r":{"a":0,"k":0,"ix":6},"o":{"a":0,"k":100,"ix":7},"sk":{"a":0,"k":0,"ix":4},"sa":{"a":0,"k":0,"ix":5},"nm":"Transform"}],"nm":"Property 1=sipCancel","np":1,"cix":2,"bm":0,"ix":1,"mn":"ADBE Vector Group","hd":false}],"ip":0,"op":123,"st":0,"bm":0}],"markers":[{"tm":0,"cm":"0","dr":0}]}